pycantphi/__init__.py
pycantphi/core/__init__.py
pycantphi/core/calculator.py
pycantphi/core/cant.py
pycantphi/core/constants.py
pycantphi/core/functions.py
pycantphi/data/__init__.py
pycantphi/data/co2_annmean_mlo.txt
pycantphi/data/mauna_loa.py
pycantphi/data/sills.csv
pycantphi/data/sills.py
pycantphi/data/__pycache__/__init__.cpython-38.pyc
pycantphi/data/__pycache__/__init__.cpython-39.pyc
pycantphi/data/__pycache__/mauna_loa.cpython-38.pyc
pycantphi/data/__pycache__/mauna_loa.cpython-39.pyc
pycantphi/data/__pycache__/sills.cpython-38.pyc
pycantphi/data/__pycache__/sills.cpython-39.pyc
pycantphi/preprocessing/__init__.py
pycantphi/preprocessing/initialisation.py
pycantphi/preprocessing/validator.py
pycantphi/utils/__init__.py
pycantphi/utils/cdiseq.py
pycantphi/utils/conversions.py
pycantphi/water_masses/__init__.py
pycantphi/water_masses/definitions.py
pycantphi/water_masses/mediterranean.py
pycantphi/water_masses/omp.py
pycantphi-0.1.1.dist-info/LICENSE
pycantphi-0.1.1.dist-info/METADATA
pycantphi-0.1.1.dist-info/WHEEL
pycantphi-0.1.1.dist-info/top_level.txt
pycantphi-0.1.1.dist-info/RECORD
