Metadata-Version: 2.2
Name: pycantphi
Version: 0.1.1
Summary: A Python library for calculating anthropogenic carbon in the North Atlantic Ocean
Author-email: Raphaël Bajon <raphael.bajon@ifremer.fr>
License: MIT
Project-URL: Homepage, https://github.com/RaphaelBajon/pycantphi
Project-URL: Documentation, https://pycantphi.readthedocs.io
Project-URL: Repository, https://github.com/RaphaelBajon/pycantphi.git
Project-URL: Bug Tracker, https://github.com/RaphaelBajon/pycantphi/issues
Keywords: oceanography,carbon,climate-science,ocean-carbon,anthropogenic-carbon
Classifier: Development Status :: 4 - Beta
Classifier: Intended Audience :: Science/Research
Classifier: License :: OSI Approved :: MIT License
Classifier: Programming Language :: Python :: 3
Classifier: Programming Language :: Python :: 3.8
Classifier: Programming Language :: Python :: 3.9
Classifier: Programming Language :: Python :: 3.10
Classifier: Programming Language :: Python :: 3.11
Classifier: Topic :: Scientific/Engineering
Classifier: Topic :: Scientific/Engineering :: Oceanography
Classifier: Topic :: Scientific/Engineering :: Atmospheric Science
Requires-Python: >=3.8
License-File: LICENSE
Requires-Dist: numpy>=1.20.0
Requires-Dist: xarray>=0.16.0
Requires-Dist: pandas>=1.3.0
Requires-Dist: scipy>=1.6.0
Requires-Dist: PyCO2SYS>=1.8.0
Requires-Dist: gsw>=3.3.0
Requires-Dist: requests>=2.25.0
Provides-Extra: dev
Requires-Dist: pytest>=7.0; extra == "dev"
Requires-Dist: pytest-cov>=3.0; extra == "dev"
Requires-Dist: pytest-xdist>=2.5; extra == "dev"
Requires-Dist: black>=22.0; extra == "dev"
Requires-Dist: isort>=5.10; extra == "dev"
Requires-Dist: flake8>=4.0; extra == "dev"
Requires-Dist: mypy>=0.950; extra == "dev"
Requires-Dist: pre-commit>=2.20; extra == "dev"
Provides-Extra: docs
Requires-Dist: sphinx>=4.5; extra == "docs"
Requires-Dist: sphinx-rtd-theme>=1.0; extra == "docs"
Requires-Dist: sphinx-autodoc-typehints>=1.18; extra == "docs"
Requires-Dist: myst-parser>=0.18; extra == "docs"
Provides-Extra: notebook
Requires-Dist: jupyter>=1.0; extra == "notebook"
Requires-Dist: matplotlib>=3.5; extra == "notebook"
Requires-Dist: seaborn>=0.11; extra == "notebook"
